{
	"name": "InputFixedLengthTextDataset",
	"properties": {
		"linkedServiceName": {
			"referenceName": "BlobStorageLinkedService",
			"type": "LinkedServiceReference"
		},
		"annotations": [],
		"type": "DelimitedText",
		"typeProperties": {
			"location": {
				"type": "AzureBlobStorageLocation",
				"fileName": "FixedLengthText.csv",
				"folderPath": "Input",
				"container": "rjadf2"
			},
			"columnDelimiter": ",",
			"escapeChar": "\\",
			"quoteChar": "\""
		},
		"schema": [
			{
				"type": "String"
			}
		]
	}
}